mailos/app.py
mailos/check_emails.py
mailos/reply.py
mailos/tools/__init__.py
mailos/tools/bash_command.py
mailos/tools/pdf_tool.py
mailos/tools/python_interpreter.py
mailos/tools/weather.py
mailos/ui/__init__.py
mailos/ui/actions.py
mailos/ui/checker_form.py
mailos/ui/checker_list.py
mailos/ui/controls.py
mailos/ui/display.py
mailos/utils/attachment_utils.py
mailos/utils/auth_utils.py
mailos/utils/config_utils.py
mailos/utils/display_utils.py
mailos/utils/email_utils.py
mailos/utils/logger_utils.py
mailos/utils/reply_utils.py
mailos/vendors/__init__.py
mailos/vendors/anthropic_llm.py
mailos/vendors/base.py
mailos/vendors/bedrock_anthropic_llm.py
mailos/vendors/config.py
mailos/vendors/factory.py
mailos/vendors/models.py
mailos/vendors/openai_llm.py
mailos-0.1.2.dist-info/LICENSE
mailos-0.1.2.dist-info/METADATA
mailos-0.1.2.dist-info/WHEEL
mailos-0.1.2.dist-info/entry_points.txt
mailos-0.1.2.dist-info/top_level.txt
mailos-0.1.2.dist-info/RECORD
