Metadata-Version: 2.1
Name: mailos
Version: 0.1.2
Summary: An AI-powered email monitoring and response system
Author-email: Ivan Iufriakov <tomatyss@gmail.com>
License: MIT License
Project-URL: Homepage, https://github.com/tomatyss/mailos
Project-URL: Repository, https://github.com/tomatyss/mailos.git
Classifier: Programming Language :: Python :: 3
Classifier: License :: OSI Approved :: MIT License
Classifier: Operating System :: OS Independent
Requires-Python: >=3.8
License-File: LICENSE
Requires-Dist: pywebio>=1.8.3
Requires-Dist: apscheduler>=3.11.0
Requires-Dist: python-dotenv>=1.0.1
Requires-Dist: openai>=1.57.0
Requires-Dist: anthropic>=0.40.0
Requires-Dist: aioboto3>=13.2.0
Requires-Dist: click>=8.1.7
Requires-Dist: requests>=2.32.3
Requires-Dist: PyPDF2>=3.0.1
Requires-Dist: reportlab>=4.2.5
Provides-Extra: dev
Requires-Dist: pytest>=6.0; extra == "dev"
Requires-Dist: pytest-asyncio; extra == "dev"
Requires-Dist: black; extra == "dev"
Requires-Dist: isort; extra == "dev"
Requires-Dist: mypy; extra == "dev"
Requires-Dist: flake8; extra == "dev"
Requires-Dist: flake8-docstrings; extra == "dev"
Requires-Dist: flake8-quotes; extra == "dev"
Requires-Dist: flake8-bugbear; extra == "dev"
Requires-Dist: pre-commit; extra == "dev"
Provides-Extra: docs
Requires-Dist: sphinx>=7.0.0; extra == "docs"
Requires-Dist: sphinx-autobuild>=2024.2.4; extra == "docs"
Requires-Dist: sphinx-rtd-theme>=2.0.0; extra == "docs"
Requires-Dist: myst-parser>=2.0.0; extra == "docs"
Requires-Dist: sphinxcontrib-mermaid>=0.9.2; extra == "docs"
